geohash_nova/__init__.py
geohash_nova/geohash_exceptions.py
geohash_nova/geohash_nova.py
geohash_nova/geohash_warnings.py
geohash_nova-1.2.0.dist-info/LICENSE
geohash_nova-1.2.0.dist-info/METADATA
geohash_nova-1.2.0.dist-info/WHEEL
geohash_nova-1.2.0.dist-info/top_level.txt
geohash_nova-1.2.0.dist-info/RECORD
