Metadata-Version: 2.2
Name: geohash-nova
Version: 1.2.0
Summary: A Geohash implementation in Python.
Author-email: IDEGUTI Masaya <fleetwood@mac.com>
License: MIT License
Project-URL: Homepage, https://github.com/layla777/geohash_py
Classifier: Programming Language :: Python :: 3
Classifier: License :: OSI Approved :: MIT License
Classifier: Operating System :: OS Independent
Requires-Python: >=3.8
License-File: LICENSE
Requires-Dist: bitarray
